scevonet/__init__.py
scevonet/net.py
scevonet/utils.py
scevonet-0.0.1.dist-info/LICENSE
scevonet-0.0.1.dist-info/METADATA
scevonet-0.0.1.dist-info/WHEEL
scevonet-0.0.1.dist-info/top_level.txt
scevonet-0.0.1.dist-info/RECORD
