Metadata-Version: 2.1
Name: scevonet
Version: 0.0.1
Summary: Tool for generation [cell state - gene program] network
Home-page: https://github.com/Qotov/scEvoNet
Author: Aleksandr Kotov
Author-email: alexander.o.kotov@gmail.com
License: UNKNOWN
Platform: UNKNOWN
Classifier: Programming Language :: Python :: 3
Classifier: License :: OSI Approved :: MIT License
Classifier: Operating System :: OS Independent
License-File: LICENSE
Requires-Dist: lightgbm (>=3.0.0)
Requires-Dist: pandas (>=0.24)
Requires-Dist: networkx (>=2.5)
